git_rebase_branches.py
git_rebase_branches-2.0.1.dist-info/licenses/LICENSE.txt
git_rebase_branches-2.0.1.dist-info/METADATA
git_rebase_branches-2.0.1.dist-info/WHEEL
git_rebase_branches-2.0.1.dist-info/entry_points.txt
git_rebase_branches-2.0.1.dist-info/top_level.txt
git_rebase_branches-2.0.1.dist-info/RECORD
