Metadata-Version: 2.4
Name: git-rebase-branches
Version: 2.0.1
Summary: Rebase multiple branches at once
Author-email: David Tucker <david@tucker.name>
License-Expression: LGPL-2.0-or-later
Project-URL: homepage, https://github.com/dmtucker/git-rebase-branches
Classifier: Development Status :: 5 - Production/Stable
Classifier: Intended Audience :: End Users/Desktop
Requires-Python: >=3.9
License-File: LICENSE.txt
Dynamic: license-file
